nave_visualization_core/__init__.py
nave_visualization_core/vis_functions.py
nave_visualization-1.11.dist-info/LICENSE
nave_visualization-1.11.dist-info/METADATA
nave_visualization-1.11.dist-info/WHEEL
nave_visualization-1.11.dist-info/top_level.txt
nave_visualization-1.11.dist-info/RECORD
