Metadata-Version: 2.1
Name: nave-visualization
Version: 1.11
Summary: A Python package for visualizing environmental data, specifically evapotranspiration, leaching risk,
Author-email: <nic@naveanalytics.com>
Classifier: Programming Language :: Python :: 3
Classifier: License :: OSI Approved :: MIT License
Classifier: Operating System :: OS Independent
License-File: LICENSE
Requires-Dist: geopandas
Requires-Dist: matplotlib
Requires-Dist: numpy
Requires-Dist: pandas
Requires-Dist: shapely
Requires-Dist: xarray[complete]
Requires-Dist: rasterio
